MANIFEST.in
basesetup.py
setup.py
jupyter_emacskeys/__init__.py
jupyter_emacskeys/init.js
jupyter_emacskeys.egg-info/PKG-INFO
jupyter_emacskeys.egg-info/SOURCES.txt
jupyter_emacskeys.egg-info/dependency_links.txt
jupyter_emacskeys.egg-info/requires.txt
jupyter_emacskeys.egg-info/top_level.txt