Metadata-Version: 1.1
Name: jupyter-emacskeys
Version: 0.2.3
Summary: Emacs-style keybindings for the Jupyter notebook
Home-page: UNKNOWN
Author: Robert T. McGibbon
Author-email: rmcgibbo@gmail.com
License: New BSD license
Platform: UNKNOWN
Classifier: Development Status :: 3 - Alpha
Classifier: Programming Language :: Python
Classifier: License :: OSI Approved
